kaggle_environments/__init__.py
kaggle_environments/agent.py
kaggle_environments/api.py
kaggle_environments/core.py
kaggle_environments/errors.py
kaggle_environments/helpers.py
kaggle_environments/main.py
kaggle_environments/schemas.json
kaggle_environments/status_codes.json
kaggle_environments/utils.py
kaggle_environments/envs/cabt/cabt.js
kaggle_environments/envs/cabt/cabt.json
kaggle_environments/envs/cabt/cabt.py
kaggle_environments/envs/cabt/cg/__init__.py
kaggle_environments/envs/cabt/cg/cg.dll
kaggle_environments/envs/cabt/cg/game.py
kaggle_environments/envs/cabt/cg/libcg.so
kaggle_environments/envs/cabt/cg/sim.py
kaggle_environments/envs/connectx/connectx.ipynb
kaggle_environments/envs/connectx/connectx.js
kaggle_environments/envs/connectx/connectx.json
kaggle_environments/envs/connectx/connectx.py
kaggle_environments/envs/football/football.ipynb
kaggle_environments/envs/football/football.json
kaggle_environments/envs/football/football.py
kaggle_environments/envs/football/helpers.py
kaggle_environments/envs/halite/__init__.py
kaggle_environments/envs/halite/halite.ipynb
kaggle_environments/envs/halite/halite.js
kaggle_environments/envs/halite/halite.json
kaggle_environments/envs/halite/halite.py
kaggle_environments/envs/halite/helpers.py
kaggle_environments/envs/hungry_geese/__init__.py
kaggle_environments/envs/hungry_geese/hungry_geese.js
kaggle_environments/envs/hungry_geese/hungry_geese.json
kaggle_environments/envs/hungry_geese/hungry_geese.py
kaggle_environments/envs/kore_fleets/__init__.py
kaggle_environments/envs/kore_fleets/helpers.py
kaggle_environments/envs/kore_fleets/kore_fleets.ipynb
kaggle_environments/envs/kore_fleets/kore_fleets.js
kaggle_environments/envs/kore_fleets/kore_fleets.json
kaggle_environments/envs/kore_fleets/kore_fleets.py
kaggle_environments/envs/kore_fleets/starter_bots/java/Bot.java
kaggle_environments/envs/kore_fleets/starter_bots/java/README.md
kaggle_environments/envs/kore_fleets/starter_bots/java/main.py
kaggle_environments-1.26.17.dist-info/entry_points.txt
kaggle_environments-1.26.17.dist-info/licenses/LICENSE
kaggle_environments-1.26.17.dist-info/WHEEL
kaggle_environments-1.26.17.dist-info/METADATA
kaggle_environments-1.26.17.dist-info/RECORD
